mcp_server_uv/__init__.py
mcp_server_uv/server.py
mcp_server_uv-0.1.1.dist-info/METADATA
mcp_server_uv-0.1.1.dist-info/WHEEL
mcp_server_uv-0.1.1.dist-info/entry_points.txt
mcp_server_uv-0.1.1.dist-info/RECORD
