Metadata-Version: 2.4
Name: mcp-server-uv
Version: 0.1.1
Summary: A MCP server project
Author-email: liuheng <liuheng@bonree.com>
Requires-Python: >=3.11
Requires-Dist: mcp>=1.6.0
